KaliLinuxMiji/README.md
KaliLinuxMiji/__init__.py
KaliLinuxMiji/__main__.py
KaliLinuxMiji/file.epub
KaliLinuxMiji/index.html
KaliLinuxMiji/css/__init__.py
KaliLinuxMiji/css/annotations.css
KaliLinuxMiji/css/main.css
KaliLinuxMiji/css/normalize.css
KaliLinuxMiji/css/popup.css
KaliLinuxMiji/font/__init__.py
KaliLinuxMiji/font/fontello.eot
KaliLinuxMiji/font/fontello.svg
KaliLinuxMiji/font/fontello.ttf
KaliLinuxMiji/font/fontello.woff
KaliLinuxMiji/img/__init__.py
KaliLinuxMiji/img/annotator-glyph-sprite.png
KaliLinuxMiji/img/annotator-icon-sprite.png
KaliLinuxMiji/img/apple-touch-icon.png
KaliLinuxMiji/img/cancelfullscreen.png
KaliLinuxMiji/img/close.png
KaliLinuxMiji/img/fullscreen.png
KaliLinuxMiji/img/loader.gif
KaliLinuxMiji/img/menu-icon.png
KaliLinuxMiji/img/save.png
KaliLinuxMiji/img/saved.png
KaliLinuxMiji/img/settings-s.png
KaliLinuxMiji/img/settings.png
KaliLinuxMiji/img/star.png
KaliLinuxMiji/js/__init__.py
KaliLinuxMiji/js/epub.js
KaliLinuxMiji/js/epub.min.js
KaliLinuxMiji/js/epub.min.map
KaliLinuxMiji/js/hooks.min.js
KaliLinuxMiji/js/hooks.min.map
KaliLinuxMiji/js/reader.js
KaliLinuxMiji/js/reader.js.map
KaliLinuxMiji/js/reader.min.js
KaliLinuxMiji/js/reader.min.map
KaliLinuxMiji/js/hooks/__init__.py
KaliLinuxMiji/js/hooks/extensions/__init__.py
KaliLinuxMiji/js/hooks/extensions/highlight.js
KaliLinuxMiji/js/libs/__init__.py
KaliLinuxMiji/js/libs/jquery.min.js
KaliLinuxMiji/js/libs/localforage.min.js
KaliLinuxMiji/js/libs/screenfull.js
KaliLinuxMiji/js/libs/screenfull.min.js
KaliLinuxMiji/js/libs/zip.min.js
KaliLinuxMiji/js/plugins/__init__.py
KaliLinuxMiji/js/plugins/hypothesis.js
KaliLinuxMiji/js/plugins/search.js
kali_linux_miji-2024.3.1.0.dist-info/METADATA
kali_linux_miji-2024.3.1.0.dist-info/WHEEL
kali_linux_miji-2024.3.1.0.dist-info/entry_points.txt
kali_linux_miji-2024.3.1.0.dist-info/top_level.txt
kali_linux_miji-2024.3.1.0.dist-info/RECORD
